.DS_Store
advbumpversion-1.2.0.dist-info/DESCRIPTION.rst
advbumpversion-1.2.0.dist-info/METADATA
advbumpversion-1.2.0.dist-info/RECORD
advbumpversion-1.2.0.dist-info/WHEEL
advbumpversion-1.2.0.dist-info/entry_points.txt
advbumpversion-1.2.0.dist-info/metadata.json
advbumpversion-1.2.0.dist-info/top_level.txt
bumpversion/__init__.py
bumpversion/__main__.py
bumpversion/functions.py
bumpversion/version_part.py
